mfglib/__init__.py
mfglib/alg/__init__.py
mfglib/alg/abc.py
mfglib/alg/fictitious_play.py
mfglib/alg/greedy_policy_given_mean_field.py
mfglib/alg/mf_omo.py
mfglib/alg/mf_omo_constraints.py
mfglib/alg/mf_omo_obj.py
mfglib/alg/mf_omo_params.py
mfglib/alg/mf_omo_residual_balancing.py
mfglib/alg/occupation_measure_inclusion.py
mfglib/alg/online_mirror_descent.py
mfglib/alg/prior_descent.py
mfglib/alg/q_fn.py
mfglib/alg/utils.py
mfglib/env/__init__.py
mfglib/env/environment.py
mfglib/env/examples/__init__.py
mfglib/env/examples/beach_bar.py
mfglib/env/examples/building_evacuation.py
mfglib/env/examples/conservative_treasure_hunting.py
mfglib/env/examples/crowd_motion.py
mfglib/env/examples/equilibrium_price.py
mfglib/env/examples/left_right.py
mfglib/env/examples/linear_quadratic.py
mfglib/env/examples/random_linear.py
mfglib/env/examples/rock_paper_scissors.py
mfglib/env/examples/susceptible_infected.py
mfglib/mean_field.py
mfglib/policy.py
mfglib/py.typed
mfglib/scoring.py
mfglib/tuning.py
mfglib-0.2.0.dist-info/LICENSE
mfglib-0.2.0.dist-info/METADATA
mfglib-0.2.0.dist-info/WHEEL
mfglib-0.2.0.dist-info/RECORD
