Metadata-Version: 2.3
Name: mfglib
Version: 0.2.0
Summary: A Library for Mean-Field Games.
License: MIT
Author: Xin Guo
Author-email: xinguo@berkeley.edu
Requires-Python: >=3.9
Classifier: License :: OSI Approved :: MIT License
Classifier: Programming Language :: Python :: 3
Classifier: Programming Language :: Python :: 3.9
Classifier: Programming Language :: Python :: 3.10
Classifier: Programming Language :: Python :: 3.11
Classifier: Programming Language :: Python :: 3.12
Classifier: Programming Language :: Python :: 3.13
Requires-Dist: numpy (>=1.0,<2.0) ; python_version < "3.10"
Requires-Dist: numpy (>=2.0,<3.0) ; python_version >= "3.10"
Requires-Dist: optuna (>=3.0,<4.0)
Requires-Dist: osqp (>=0.0,<1.0)
Requires-Dist: rich (>=14.0,<15.0)
Requires-Dist: scipy (<1.13) ; python_version < "3.10"
Requires-Dist: scipy (>=1.13,<2.0) ; python_version >= "3.10"
Requires-Dist: torch (>=2.0,<3.0)
Requires-Dist: typing-extensions ; python_version < "3.11"
Project-URL: Documentation, https://mfglib.readthedocs.io/en/latest/
